README.md
setup.py
src/fedservice/__init__.py
src/fedservice/exception.py
src/fedservice/keybundle.py
src/fedservice/message.py
src/fedservice/meta_api.py
src/fedservice/utils.py
src/fedservice.egg-info/PKG-INFO
src/fedservice.egg-info/SOURCES.txt
src/fedservice.egg-info/dependency_links.txt
src/fedservice.egg-info/not-zip-safe
src/fedservice.egg-info/requires.txt
src/fedservice.egg-info/top_level.txt
src/fedservice/entity_statement/__init__.py
src/fedservice/entity_statement/cache.py
src/fedservice/entity_statement/collect.py
src/fedservice/entity_statement/constraints.py
src/fedservice/entity_statement/construct.py
src/fedservice/entity_statement/create.py
src/fedservice/entity_statement/policy.py
src/fedservice/entity_statement/statement.py
src/fedservice/entity_statement/trust_mark.py
src/fedservice/entity_statement/utils.py
src/fedservice/entity_statement/verify.py
src/fedservice/metadata_api/__init__.py
src/fedservice/metadata_api/db.py
src/fedservice/metadata_api/fs.py
src/fedservice/metadata_api/fs2.py
src/fedservice/op/__init__.py
src/fedservice/op/authorization.py
src/fedservice/op/federation_api.py
src/fedservice/op/provider_config.py
src/fedservice/op/registration.py
src/fedservice/op/signing_service.py
src/fedservice/op/add_on/__init__.py
src/fedservice/op/add_on/automatic_registration.py
src/fedservice/rp/__init__.py
src/fedservice/rp/authorization.py
src/fedservice/rp/provider_info_discovery.py
src/fedservice/rp/registration.py